dagster_postgres/__init__.py
dagster_postgres/py.typed
dagster_postgres/pynotify.py
dagster_postgres/storage.py
dagster_postgres/utils.py
dagster_postgres/version.py
dagster_postgres/alembic/alembic.ini
dagster_postgres/event_log/__init__.py
dagster_postgres/event_log/event_log.py
dagster_postgres/event_log/event_watcher.py
dagster_postgres/run_storage/__init__.py
dagster_postgres/run_storage/run_storage.py
dagster_postgres/schedule_storage/__init__.py
dagster_postgres/schedule_storage/schedule_storage.py
dagster_postgres-1.0.5.dist-info/LICENSE
dagster_postgres-1.0.5.dist-info/METADATA
dagster_postgres-1.0.5.dist-info/WHEEL
dagster_postgres-1.0.5.dist-info/top_level.txt
dagster_postgres-1.0.5.dist-info/RECORD
